fixedwidth/__init__.py
fixedwidth/fixed_width_record.py
fixedwidth/fixed_width_spec.py
simplefixedwidth/__init__.py
simplefixedwidth/fixed_width_record.py
simplefixedwidth/fixed_width_spec.py
SimpleFixedWidth-0.0.2.dist-info/LICENSE
SimpleFixedWidth-0.0.2.dist-info/METADATA
SimpleFixedWidth-0.0.2.dist-info/WHEEL
SimpleFixedWidth-0.0.2.dist-info/top_level.txt
SimpleFixedWidth-0.0.2.dist-info/RECORD
