Metadata-Version: 2.1
Name: SimpleFixedWidth
Version: 0.0.2
Summary: A simple python library for quickly parsing records in a fixed width format.
Home-page: https://github.com/N-C-C/simplefixedwidth
Author: John Glasgow
Author-email: jglasgow@northampton.edu
License: UNKNOWN
Platform: UNKNOWN
Classifier: Programming Language :: Python :: 3.7
Classifier: Operating System :: OS Independent
